xelytics/__init__.py
xelytics/__version__.py
xelytics/engine.py
xelytics/exceptions.py
xelytics/cli/__init__.py
xelytics/cli/main.py
xelytics/core/__init__.py
xelytics/core/features.py
xelytics/core/ingestion.py
xelytics/core/profiler.py
xelytics/insights/__init__.py
xelytics/insights/rules.py
xelytics/llm/__init__.py
xelytics/llm/narrator.py
xelytics/llm/provider.py
xelytics/llm/providers/__init__.py
xelytics/llm/providers/openai.py
xelytics/schemas/__init__.py
xelytics/schemas/config.py
xelytics/schemas/inputs.py
xelytics/schemas/metadata.py
xelytics/schemas/outputs.py
xelytics/stats/__init__.py
xelytics/stats/engine.py
xelytics/stats/planner.py
xelytics/stats/tests.py
xelytics/viz/__init__.py
xelytics/viz/generator.py
xelytics/viz/selector.py
xelytics_core-0.1.0.dist-info/METADATA
xelytics_core-0.1.0.dist-info/WHEEL
xelytics_core-0.1.0.dist-info/entry_points.txt
xelytics_core-0.1.0.dist-info/top_level.txt
xelytics_core-0.1.0.dist-info/RECORD
