Metadata-Version: 2.4
Name: xelytics-core
Version: 0.1.0
Summary: Pure analytics engine for statistical analysis and insight generation
Author: Xelytics Team
License: MIT
Classifier: Development Status :: 3 - Alpha
Classifier: Intended Audience :: Developers
Classifier: License :: OSI Approved :: MIT License
Classifier: Programming Language :: Python :: 3
Classifier: Programming Language :: Python :: 3.9
Classifier: Programming Language :: Python :: 3.10
Classifier: Programming Language :: Python :: 3.11
Classifier: Programming Language :: Python :: 3.12
Requires-Python: >=3.9
Requires-Dist: pandas>=2.1.0
Requires-Dist: numpy>=1.24.0
Requires-Dist: scipy>=1.11.0
Requires-Dist: scikit-learn>=1.3.0
Requires-Dist: statsmodels>=0.14.0
Requires-Dist: pingouin>=0.5.3
Requires-Dist: plotly>=5.17.0
Provides-Extra: llm
Requires-Dist: openai>=1.6.0; extra == "llm"
Requires-Dist: groq>=0.4.0; extra == "llm"
Requires-Dist: httpx>=0.25.0; extra == "llm"
Provides-Extra: dev
Requires-Dist: pytest>=7.4.0; extra == "dev"
Requires-Dist: pytest-asyncio>=0.21.0; extra == "dev"
Requires-Dist: pytest-cov>=4.1.0; extra == "dev"
Requires-Dist: black>=23.11.0; extra == "dev"
Requires-Dist: mypy>=1.7.0; extra == "dev"
